MANIFEST.in
README.md
VERSION
requirements.txt
setup.cfg
setup.py
tartiflette_plugin_apollo_federation/__init__.py
tartiflette_plugin_apollo_federation/bake.py
tartiflette_plugin_apollo_federation.egg-info/PKG-INFO
tartiflette_plugin_apollo_federation.egg-info/SOURCES.txt
tartiflette_plugin_apollo_federation.egg-info/dependency_links.txt
tartiflette_plugin_apollo_federation.egg-info/requires.txt
tartiflette_plugin_apollo_federation.egg-info/top_level.txt