Metadata-Version: 2.1
Name: tartiflette-plugin-apollo-federation
Version: 0.0.4
Summary: Plugin to compose your Tartiflette Graphql service in an Apollo federation
Home-page: https://github.com/remorses/tartiflette_plugin_apollo_federation
Author: Tommaso De Rossi
Author-email: daer.tommy@gmail.com
License: Apache Software License 2.0
Keywords: tartiflette,apollo,federation,graphql
Platform: UNKNOWN
Classifier: Intended Audience :: Information Technology
Classifier: Programming Language :: Python :: 3
Classifier: Programming Language :: Python :: 3.6
Classifier: Programming Language :: Python :: 3.7
